[
  { "name": "Alabama", "nickName": "Yellowhammer State, Area: 50,744"},
  { "name": "Alaska", "nickName": "The Last Frontier, Area: 571,951" },
  { "name": "Arizona", "nickName": "The Grand Canyon State, Area: 113,635" },
  { "name": "Arkansas", "nickName": "The Natural State, Area: 52,068" },
  { "name": "California", "nickName": "The Golden State, Area: 155,959" },
  { "name": "Colorado", "nickName": "The Centennial State, Area: 103,718" },
  { "name": "Connecticut", "nickName": "The Constitution State, Area: 4,845" },
  { "name": "Delaware", "nickName": "The First State, Area: 1,954" },
  { "name": "Florida", "nickName": "The Sunshine State, Area: 53,927" },
  { "name": "Georgia", "nickName": "The Peach State, Area: 57,906" },
  { "name": "Hawaii", "nickName": "The Aloha State, Area: 6,423" },
  { "name": "Idaho", "nickName": "The Gem State, Area: 82,747" },
  { "name": "Illinois", "nickName": "Prairie State, Area: 55,584" },
  { "name": "Indiana", "nickName": "The Hoosier State, Area: 35,867" },
  { "name": "Iowa", "nickName": "The Hawkeye State, Area: 55,869" },
  { "name": "Kansas", "nickName": "The Sunflower State, Area: 81,815" },
  { "name": "Kentucky", "nickName": "The Bluegrass State, Area: 39,728" },
  { "name": "Louisiana", "nickName": "The Pelican State, Area: 43,562" },
  { "name": "Maine", "nickName": "The Pine Tree State, Area: 30,862" },
  { "name": "Maryland", "nickName": "The Old Line State, Area: 9,774" },
  { "name": "Massachusetts", "nickName": "The Bay State, Area: 7,840" },
  { "name": "Michigan", "nickName": "The Great Lakes State, Area: 56,804" },
  { "name": "Minnesota", "nickName": "The North Star State, Area: 79,610" },
  { "name": "Mississippi", "nickName": "The Magnolia State, Area: 46,907" },
  { "name": "Missouri", "nickName": "The Show Me State, Area: 68,886" },
  { "name": "Montana", "nickName": "The Treasure State, Area: 145,552" },
  { "name": "Nebraska", "nickName": "The Cornhusker State, Area: 76,872" },
  { "name": "Nevada", "nickName": "The Silver State, Area: 109,826" },
  { "name": "New Hampshire", "nickName": "The Granite State, Area: 8,968" },
  { "name": "New Jersey", "nickName": "The Garden State, Area: 7,417" },
  { "name": "New Mexico", "nickName": "The Land of Enchantment, Area: 121,356" },
  { "name": "New York", "nickName": "The Empire State, Area: 47,214" },
  { "name": "North Carolina", "nickName": "The Tar Heel State, Area: 48,711" },
  { "name": "North Dakota", "nickName": "The Peace Garden State, Area: 68,976" },
  { "name": "Ohio", "nickName": "The Buckeye State, Area: 40,948" },
  { "name": "Oklahoma", "nickName": "The Sooner State,  Area: 68,667" },
  { "name": "Oregon", "nickName": "The Beaver State, Area: 95,997" },
  { "name": "Pennsylvania", "nickName": "The Keystone State, Area: 44,817" },
  { "name": "Rhode Island", "nickName": "The Ocean State, Area: 1,045" },
  { "name": "South Carolina", "nickName": "The Palmetto State, Area: 30,109" },
  { "name": "South Dakota", "nickName": "Mount Rushmore State, Area: 75,885" },
  { "name": "Tennessee", "nickName": "The Volunteer State, Area: 41,217" },
  { "name": "Texas", "nickName": "The Lone Star State, Area: 261,797" },
  { "name": "Utah", "nickName": "The Beehive State, Area: 82,144" },
  { "name": "Vermont", "nickName": "The Green Mountain State, Area: 9,250" },
  { "name": "Virginia", "nickName": "The Old Dominion State, Area: 39,594" },
  { "name": "Washington", "nickName": "The Evergreen State, Area: 66,544" },
  { "name": "West Virginia", "nickName": "The Mountain State, Area: 24,078" },
  { "name": "Wisconsin", "nickName": "The Badger State, Area: 54,310" },
  { "name": "Wyoming", "nickName": "The Equality or Cowboy State, Area: 97,100" },


]
